ai_sudoku_solver/__init__.py
ai_sudoku_solver-1.0.7.dist-info/LICENSE
ai_sudoku_solver-1.0.7.dist-info/WHEEL
ai_sudoku_solver-1.0.7.dist-info/METADATA
ai_sudoku_solver-1.0.7.dist-info/RECORD
