Metadata-Version: 2.1
Name: ai-sudoku-solver
Version: 1.0.7
Summary: A python library for solving sudoku puzzles using artificial neural networks
Author: Ritvik19
Author-email: rastogiritvik99@gmail.com
Requires-Python: >=3.7,<4.0
Classifier: Programming Language :: Python :: 3
Classifier: Programming Language :: Python :: 3.7
Classifier: Programming Language :: Python :: 3.8
Classifier: Programming Language :: Python :: 3.9
Requires-Dist: huggingface-hub (==0.2.1)
Requires-Dist: numpy (==1.20.1)
Requires-Dist: tensorflow (==2.7.0)
Requires-Dist: tqdm (==4.59.0)
